src/__init__.py
src/functions.py
Bubbelz_Logger-0.0.1.dist-info/LICENSE
Bubbelz_Logger-0.0.1.dist-info/METADATA
Bubbelz_Logger-0.0.1.dist-info/WHEEL
Bubbelz_Logger-0.0.1.dist-info/top_level.txt
Bubbelz_Logger-0.0.1.dist-info/RECORD
