Metadata-Version: 2.1
Name: Bubbelz Logger
Version: 0.0.1
Summary: PyPI Package for Bubbelz Logger functions
Home-page: https://github.com/javatechy/dokr
Author: Bubbelz
Author-email: info@bubbelz.life
Classifier: Programming Language :: Python :: 3
Classifier: License :: Other/Proprietary License
Classifier: Operating System :: OS Independent
License-File: LICENSE
